playlistfromsong/__init__.py
playlistfromsong/cli.py
playlistfromsong/playlistfromsong.py
playlistfromsong/server.py
playlistfromsong/assets/css/style.css
playlistfromsong/assets/css/style2.css
playlistfromsong/assets/js/html5media.min.js
playlistfromsong/assets/js/index.js
playlistfromsong/assets/js/jquery.min.js
playlistfromsong/assets/js/prefixfree.min.js
playlistfromsong/templates/index.html
playlistfromsong-2.2.2.dist-info/DESCRIPTION.rst
playlistfromsong-2.2.2.dist-info/METADATA
playlistfromsong-2.2.2.dist-info/RECORD
playlistfromsong-2.2.2.dist-info/WHEEL
playlistfromsong-2.2.2.dist-info/entry_points.txt
playlistfromsong-2.2.2.dist-info/metadata.json
playlistfromsong-2.2.2.dist-info/top_level.txt
