Metadata-Version: 2.0
Name: playlistfromsong
Version: 2.2.2
Summary: Generate an offline playlist from a single song
Home-page: https://github.com/schollz/playlistfromsong
Author: Zack
Author-email: hypercube.platforms@gmail.com
License: MIT license
Keywords: playlistfromsong
Platform: UNKNOWN
Classifier: Development Status :: 2 - Pre-Alpha
Classifier: Intended Audience :: Developers
Classifier: License :: OSI Approved :: MIT License
Classifier: Natural Language :: English
Classifier: Programming Language :: Python :: 2
Classifier: Programming Language :: Python :: 2.6
Classifier: Programming Language :: Python :: 2.7
Classifier: Programming Language :: Python :: 3
Classifier: Programming Language :: Python :: 3.3
Classifier: Programming Language :: Python :: 3.4
Classifier: Programming Language :: Python :: 3.5
Requires-Dist: Click (>=6.0)
Requires-Dist: appdirs
Requires-Dist: beautifulsoup4
Requires-Dist: flask
Requires-Dist: pyyaml
Requires-Dist: requests
Requires-Dist: waitress
Requires-Dist: youtube-dl
